PyTravisCI/__about__.py
PyTravisCI/__init__.py
PyTravisCI/exceptions.py
PyTravisCI/requester.py
PyTravisCI/standardization.py
PyTravisCI/travis_ci.py
PyTravisCI/communicator/__init__.py
PyTravisCI/communicator/_all.py
PyTravisCI/communicator/active.py
PyTravisCI/communicator/base.py
PyTravisCI/communicator/beta_feature.py
PyTravisCI/communicator/beta_features.py
PyTravisCI/communicator/branch.py
PyTravisCI/communicator/branches.py
PyTravisCI/communicator/broadcasts.py
PyTravisCI/communicator/build.py
PyTravisCI/communicator/builds.py
PyTravisCI/communicator/cache.py
PyTravisCI/communicator/caches.py
PyTravisCI/communicator/cron.py
PyTravisCI/communicator/crons.py
PyTravisCI/communicator/env_var.py
PyTravisCI/communicator/env_vars.py
PyTravisCI/communicator/job.py
PyTravisCI/communicator/jobs.py
PyTravisCI/communicator/key_pair.py
PyTravisCI/communicator/key_pair_generated.py
PyTravisCI/communicator/lint.py
PyTravisCI/communicator/log.py
PyTravisCI/communicator/messages.py
PyTravisCI/communicator/organization.py
PyTravisCI/communicator/organizations.py
PyTravisCI/communicator/repositories.py
PyTravisCI/communicator/repository.py
PyTravisCI/communicator/request.py
PyTravisCI/communicator/requests.py
PyTravisCI/communicator/setting.py
PyTravisCI/communicator/settings.py
PyTravisCI/communicator/stages.py
PyTravisCI/communicator/user.py
PyTravisCI/defaults/__init__.py
PyTravisCI/defaults/access_points.py
PyTravisCI/defaults/formats.py
PyTravisCI/defaults/requester.py
PyTravisCI/defaults/states.py
PyTravisCI/encryption/__init__.py
PyTravisCI/encryption/data.py
PyTravisCI/encryption/file.py
PyTravisCI/resource_types/__init__.py
PyTravisCI/resource_types/_all.py
PyTravisCI/resource_types/active.py
PyTravisCI/resource_types/base.py
PyTravisCI/resource_types/beta_feature.py
PyTravisCI/resource_types/beta_features.py
PyTravisCI/resource_types/branch.py
PyTravisCI/resource_types/branches.py
PyTravisCI/resource_types/broadcast.py
PyTravisCI/resource_types/broadcasts.py
PyTravisCI-2.0.2.dist-info/LICENSE
PyTravisCI-2.0.2.dist-info/METADATA
PyTravisCI-2.0.2.dist-info/WHEEL
PyTravisCI-2.0.2.dist-info/top_level.txt
PyTravisCI-2.0.2.dist-info/RECORD
