Metadata-Version: 2.1
Name: PyTravisCI
Version: 2.0.2
Summary: Just another Python API for Travis CI (API).
Home-page: https://github.com/funilrys/PyTravisCI
Author: funilrys
Author-email: contact@funilrys.com
License: MIT
Keywords: Travis CI,Travis,CI,API
Platform: any
Classifier: Environment :: Console
Classifier: Topic :: Internet
Classifier: Development Status :: 5 - Production/Stable
Classifier: Intended Audience :: Developers
Classifier: Programming Language :: Python
Classifier: Programming Language :: Python :: 3
Classifier: License :: OSI Approved
Classifier: License :: OSI Approved :: MIT License
Requires-Python: >=3.6, <4
Requires-Dist: setuptools
Requires-Dist: requests
Requires-Dist: cryptography
